dirng/__init__.py
dirng/cg_methods.py
dirng/device_methods.py
dirng/devices.py
dirng/eat_methods.py
dirng/games.py
dirng/protocol.py
dirng/qubit_methods.py
dirng/etc/dirng_config.json
dirng-1.0.1.dist-info/LICENSE
dirng-1.0.1.dist-info/METADATA
dirng-1.0.1.dist-info/WHEEL
dirng-1.0.1.dist-info/top_level.txt
dirng-1.0.1.dist-info/RECORD
