Metadata-Version: 2.1
Name: dirng
Version: 1.0.1
Summary: Designing quantum-secure randomness expansion protocols
Home-page: https://github.com/peterjbrown519/dirng
Author: Peter J. Brown
Author-email: pjb519@york.ac.uk
License: GNU
Platform: UNKNOWN
Classifier: Programming Language :: Python :: 3
Classifier: License :: OSI Approved :: GNU General Public License v3 or later (GPLv3+)
Classifier: Operating System :: OS Independent
Classifier: Topic :: Scientific/Engineering :: Physics
Requires-Dist: numpy
Requires-Dist: scipy
Requires-Dist: tabulate
Requires-Dist: ncpol2sdpa
Requires-Dist: sympy
